D365BCAPI/D365BCv1API.py
D365BCAPI/__init__.py
D365BCAPI/sample.py
tests/__init__.py
tests/test.py
D365BCAPI_GEDASB-0.0.1b1.dist-info/LICENSE
D365BCAPI_GEDASB-0.0.1b1.dist-info/METADATA
D365BCAPI_GEDASB-0.0.1b1.dist-info/WHEEL
D365BCAPI_GEDASB-0.0.1b1.dist-info/top_level.txt
D365BCAPI_GEDASB-0.0.1b1.dist-info/RECORD
