Metadata-Version: 2.1
Name: D365BCAPI-GEDASB
Version: 0.0.1b1
Summary: Dynamics 365 Business Central API connector
Home-page: https://github.com/gedasb/D365BCAPI
Author: Gedas B
Author-email: gedasb@outlook.com
License: UNKNOWN
Keywords: Microsoft Dynamics 365 Business Central NAV API
Platform: UNKNOWN
Classifier: Programming Language :: Python :: 3
Classifier: License :: OSI Approved :: MIT License
Classifier: Operating System :: OS Independent
Requires-Python: >=3.6
Requires-Dist: requests
